cnnClassifier/__init__.py
cnnClassifier/components/__init__.py
cnnClassifier/components/data_ingestion.py
cnnClassifier/components/evaluation.py
cnnClassifier/components/prepare_base_model.py
cnnClassifier/components/prepare_callbacks.py
cnnClassifier/components/training.py
cnnClassifier/config/__init__.py
cnnClassifier/config/configuration.py
cnnClassifier/constants/__init__.py
cnnClassifier/entity/__init__.py
cnnClassifier/entity/config_entity.py
cnnClassifier/pipeline/__init__.py
cnnClassifier/pipeline/predict.py
cnnClassifier/pipeline/stage_01_data_ingestion.py
cnnClassifier/pipeline/stage_02_prepare_base_model.py
cnnClassifier/pipeline/stage_03_training.py
cnnClassifier/pipeline/stage_04_evaluation.py
cnnClassifier/utils/__init__.py
cnnClassifier/utils/common.py
cnnClassifier-0.0.0.dist-info/LICENSE
cnnClassifier-0.0.0.dist-info/METADATA
cnnClassifier-0.0.0.dist-info/WHEEL
cnnClassifier-0.0.0.dist-info/top_level.txt
cnnClassifier-0.0.0.dist-info/RECORD
