Metadata-Version: 2.1
Name: cnnClassifier
Version: 0.0.0
Summary: small python package for cnn app.
Home-page: https://github.com/pranay518/chicken-disease-classification-project
Author: pranay518
Author-email: pranayprabhat518@gmail.com
Project-URL: Bug Tracker, https://github.com/pranay518/chicken-disease-classification-project/issues
License-File: LICENSE
